README.md
jdb.py
setup.cfg
setup.py
jdb.egg-info/PKG-INFO
jdb.egg-info/SOURCES.txt
jdb.egg-info/dependency_links.txt
jdb.egg-info/not-zip-safe
jdb.egg-info/top_level.txt