Metadata-Version: 2.1
Name: jdb
Version: 1.0
Summary: A library for the python language that makes it easy to use all the goodies of JSON.
Author-email: neadond@gmail.com
